safeds_examples/__init__.py
safeds_examples/tabular/__init__.py
safeds_examples/tabular/_house_sales/__init__.py
safeds_examples/tabular/_house_sales/_house_sales.py
safeds_examples/tabular/_house_sales/data/house_sales.csv
safeds_examples/tabular/_titanic/__init__.py
safeds_examples/tabular/_titanic/_titanic.py
safeds_examples/tabular/_titanic/data/titanic.csv
safeds_examples/tabular/containers/__init__.py
safeds_examples/tabular/containers/_example_table.py
safe_ds_examples-0.17.0.dist-info/LICENSE
safe_ds_examples-0.17.0.dist-info/METADATA
safe_ds_examples-0.17.0.dist-info/WHEEL
safe_ds_examples-0.17.0.dist-info/RECORD
