Metadata-Version: 2.1
Name: safe-ds-examples
Version: 0.17.0
Summary: Ready-to-use examples for the Safe-DS Python library.
Home-page: https://github.com/Safe-DS/Library-Examples
License: MIT
Keywords: data-science,machine-learning,usability,learnability
Author: Lars Reimann
Author-email: mail@larsreimann.com
Requires-Python: >=3.11,<3.12
Classifier: License :: OSI Approved :: MIT License
Classifier: Programming Language :: Python :: 3
Classifier: Programming Language :: Python :: 3.11
Requires-Dist: safe-ds (>=0.17,<0.18)
Project-URL: Documentation, https://library-examples.safe-ds.com
Project-URL: Repository, https://github.com/Safe-DS/Library-Examples
